{
  "images": [
    {
      "filename": "1810313773056.bmp",
      "hands": [
        {
          "hand_index": 0,
          "landmarks": [
            {
              "x": 0.4019952118396759,
              "y": 0.41952478885650635,
              "z": 2.1967241536913207e-07
            },
            {
              "x": 0.3975226581096649,
              "y": 0.38194844126701355,
              "z": -0.03758098930120468
            },
            {
              "x": 0.3618256449699402,
              "y": 0.35297390818595886,
              "z": -0.039988502860069275
            },
            {
              "x": 0.30549025535583496,
              "y": 0.34511029720306396,
              "z": -0.036075543612241745
            },
            {
              "x": 0.26614317297935486,
              "y": 0.34502169489860535,
              "z": -0.0294349268078804
            },
            {
              "x": 0.36813482642173767,
              "y": 0.32558467984199524,
              "z": 0.017874939367175102
            },
            {
              "x": 0.34588366746902466,
              "y": 0.3043336272239685,
              "z": 0.021409599110484123
            },
            {
              "x": 0.3380679786205292,
              "y": 0.29088833928108215,
              "z": 0.015523549169301987
            },
            {
              "x": 0.3325625956058502,
              "y": 0.2807735800743103,
              "z": 0.00988879892975092
            },
            {
              "x": 0.3441351652145386,
              "y": 0.3395572900772095,
              "z": 0.036869507282972336
            },
            {
              "x": 0.31292223930358887,
              "y": 0.32419541478157043,
              "z": 0.03110044077038765
            },
            {
              "x": 0.31519177556037903,
              "y": 0.32937946915626526,
              "z": 0.01260699238628149
            },
            {
              "x": 0.3243647813796997,
              "y": 0.33947381377220154,
              "z": 0.0038487131241708994
            },
            {
              "x": 0.3277924954891205,
              "y": 0.3547593355178833,
              "z": 0.0505523681640625
            },
            {
              "x": 0.30028510093688965,
              "y": 0.3417592942714691,
              "z": 0.03783802315592766
            },
            {
              "x": 0.306090384721756,
              "y": 0.3499337136745453,
              "z": 0.017434118315577507
            },
            {
              "x": 0.31556129455566406,
              "y": 0.3606233596801758,
              "z": 0.010450761765241623
            },
            {
              "x": 0.31794899702072144,
              "y": 0.37007707357406616,
              "z": 0.06186015531420708
            },
            {
              "x": 0.2954055368900299,
              "y": 0.3611833155155182,
              "z": 0.049771133810281754
            },
            {
              "x": 0.2981136739253998,
              "y": 0.3661884367465973,
              "z": 0.037480417639017105
            },
            {
              "x": 0.3072446584701538,
              "y": 0.3704366683959961,
              "z": 0.033436838537454605
            }
          ]
        }
      ]
    },
    {
      "filename": "1810480365568.bmp",
      "hands": [
        {
          "hand_index": 0,
          "landmarks": [
            {
              "x": 0.41921964287757874,
              "y": 0.4621715545654297,
              "z": -3.308293727855016e-08
            },
            {
              "x": 0.4244067370891571,
              "y": 0.4082452356815338,
              "z": -0.015594868920743465
            },
            {
              "x": 0.39691415429115295,
              "y": 0.3600860834121704,
              "z": -0.01983371190726757
            },
            {
              "x": 0.3521334230899811,
              "y": 0.3304508328437805,
              "z": -0.027146631851792336
            },
            {
              "x": 0.31035315990448,
              "y": 0.3098491132259369,
              "z": -0.032954633235931396
            },
            {
              "x": 0.3398403525352478,
              "y": 0.34173494577407837,
              "z": 0.01358622033149004
            },
            {
              "x": 0.29325905442237854,
              "y": 0.30540335178375244,
              "z": -0.005855870433151722
            },
            {
              "x": 0.30121928453445435,
              "y": 0.29290133714675903,
              "z": -0.025842444971203804
            },
            {
              "x": 0.31873518228530884,
              "y": 0.2967037856578827,
              "z": -0.03724699839949608
            },
            {
              "x": 0.3192936182022095,
              "y": 0.3572100102901459,
              "z": 0.010663613677024841
            },
            {
              "x": 0.2621452212333679,
              "y": 0.3185088038444519,
              "z": -0.01214755978435278
            },
            {
              "x": 0.2823208272457123,
              "y": 0.3150934875011444,
              "z": -0.03611326217651367
            },
            {
              "x": 0.3084733188152313,
              "y": 0.32973527908325195,
              "z": -0.049605369567871094
            },
            {
              "x": 0.3038845360279083,
              "y": 0.37558284401893616,
              "z": 0.0031284852884709835
            },
            {
              "x": 0.2511598765850067,
              "y": 0.3391985595226288,
              "z": -0.01801009103655815
            },
            {
              "x": 0.2713317275047302,
              "y": 0.33461853861808777,
              "z": -0.03437354788184166
            },
            {
              "x": 0.29801473021507263,
              "y": 0.35014861822128296,
              "z": -0.042297083884477615
            },
            {
              "x": 0.29395782947540283,
              "y": 0.39670097827911377,
              "z": -0.006333997007459402
            },
            {
              "x": 0.2635955214500427,
              "y": 0.3690875172615051,
              "z": -0.023156771436333656
            },
            {
              "x": 0.28075575828552246,
              "y": 0.3600429594516754,
              "z": -0.03351006284356117
            },
            {
              "x": 0.30315065383911133,
              "y": 0.3660915195941925,
              "z": -0.039274364709854126
            }
          ]
        }
      ]
    },
    {
      "filename": "1817078923264.bmp",
      "hands": [
        {
          "hand_index": 0,
          "landmarks": [
            {
              "x": 0.6295117139816284,
              "y": 0.38886499404907227,
              "z": -4.677892206927936e-07
            },
            {
              "x": 0.563687264919281,
              "y": 0.3658503592014313,
              "z": -0.014704320579767227
            },
            {
              "x": 0.5345962047576904,
              "y": 0.32429569959640503,
              "z": -0.0177899319678545
            },
            {
              "x": 0.5240166783332825,
              "y": 0.2843649983406067,
              "z": -0.012571247294545174
            },
            {
              "x": 0.5303478837013245,
              "y": 0.2607460916042328,
              "z": -0.003716211998835206
            },
            {
              "x": 0.6112334132194519,
              "y": 0.28848105669021606,
              "z": -0.03972348943352699
            },
            {
              "x": 0.5691375136375427,
              "y": 0.25267642736434937,
              "z": -0.023593168705701828
            },
            {
              "x": 0.5481449961662292,
              "y": 0.26576530933380127,
              "z": -0.002201463095843792
            },
            {
              "x": 0.54352867603302,
              "y": 0.2834564745426178,
              "z": 0.011018455028533936
            },
            {
              "x": 0.6511985063552856,
              "y": 0.2915986180305481,
              "z": -0.024614011868834496
            },
            {
              "x": 0.599901020526886,
              "y": 0.2672630846500397,
              "z": -0.006415065377950668
            },
            {
              "x": 0.5769729614257812,
              "y": 0.2830091118812561,
              "z": 0.008510713465511799
            },
            {
              "x": 0.5742448568344116,
              "y": 0.2987442910671234,
              "z": 0.013211773708462715
            },
            {
              "x": 0.6765846014022827,
              "y": 0.3036802113056183,
              "z": -0.005658015143126249
            },
            {
              "x": 0.6299260258674622,
              "y": 0.28216078877449036,
              "z": 0.007520085666328669
            },
            {
              "x": 0.6093239188194275,
              "y": 0.2925574481487274,
              "z": 0.013771341182291508
            },
            {
              "x": 0.6071478128433228,
              "y": 0.30919381976127625,
              "z": 0.012278630398213863
            },
            {
              "x": 0.6913444995880127,
              "y": 0.3172670304775238,
              "z": 0.014154301024973392
            },
            {
              "x": 0.6525978446006775,
              "y": 0.30151575803756714,
              "z": 0.02019082009792328
            },
            {
              "x": 0.6362159848213196,
              "y": 0.3087487816810608,
              "z": 0.0239885076880455
            },
            {
              "x": 0.6355254054069519,
              "y": 0.3209083080291748,
              "z": 0.024803271517157555
            }
          ]
        }
      ]
    },
    {
      "filename": "1818778533888.bmp",
      "hands": [
        {
          "hand_index": 0,
          "landmarks": [
            {
              "x": 0.5040673017501831,
              "y": 0.37025853991508484,
              "z": -3.125209389054362e-07
            },
            {
              "x": 0.4163559079170227,
              "y": 0.35187000036239624,
              "z": -0.026361895725131035
            },
            {
              "x": 0.33650895953178406,
              "y": 0.3591969907283783,
              "z": -0.00745561346411705
            },
            {
              "x": 0.2814599573612213,
              "y": 0.38842400908470154,
              "z": 0.015362764708697796
            },
            {
              "x": 0.2519417703151703,
              "y": 0.41571953892707825,
              "z": 0.04349244758486748
            },
            {
              "x": 0.32501858472824097,
              "y": 0.3223785161972046,
              "z": 0.07485124468803406
            },
            {
              "x": 0.2692679762840271,
              "y": 0.3655327260494232,
              "z": 0.08247210085391998
            },
            {
              "x": 0.28059276938438416,
              "y": 0.3822227716445923,
              "z": 0.07281534373760223
            },
            {
              "x": 0.3032671809196472,
              "y": 0.38378292322158813,
              "z": 0.06948406249284744
            },
            {
              "x": 0.34737318754196167,
              "y": 0.34825649857521057,
              "z": 0.0981382206082344
            },
            {
              "x": 0.3000473082065582,
              "y": 0.38660910725593567,
              "z": 0.09819857031106949
            },
            {
              "x": 0.3272823989391327,
              "y": 0.3885163962841034,
              "z": 0.06888790428638458
            },
            {
              "x": 0.36126285791397095,
              "y": 0.38255205750465393,
              "z": 0.05511118844151497
            },
            {
              "x": 0.3699788749217987,
              "y": 0.3736591041088104,
              "z": 0.11416956037282944
            },
            {
              "x": 0.32772335410118103,
              "y": 0.4026761054992676,
              "z": 0.10283438116312027
            },
            {
              "x": 0.35453036427497864,
              "y": 0.3994899094104767,
              "z": 0.06760207563638687
            },
            {
              "x": 0.3842605948448181,
              "y": 0.3910320997238159,
              "z": 0.05325208604335785
            },
            {
              "x": 0.38784900307655334,
              "y": 0.3950611650943756,
              "z": 0.1293925791978836
            },
            {
              "x": 0.3582126498222351,
              "y": 0.41026630997657776,
              "z": 0.1155976876616478
            },
            {
              "x": 0.38428622484207153,
              "y": 0.4068244695663452,
              "z": 0.09500742703676224
            },
            {
              "x": 0.40951648354530334,
              "y": 0.3959353566169739,
              "z": 0.08777303993701935
            }
          ]
        }
      ]
    },
    {
      "filename": "1819944812544.bmp",
      "hands": [
        {
          "hand_index": 0,
          "landmarks": [
            {
              "x": 0.6048274636268616,
              "y": 0.40032759308815,
              "z": 1.6583084061494446e-07
            },
            {
              "x": 0.538669228553772,
              "y": 0.37315911054611206,
              "z": -0.0034242768306285143
            },
            {
              "x": 0.4988979697227478,
              "y": 0.33596616983413696,
              "z": 0.01037651114165783
            },
            {
              "x": 0.48064255714416504,
              "y": 0.3062770664691925,
              "z": 0.029808426275849342
            },
            {
              "x": 0.4774526357650757,
              "y": 0.281455934047699,
              "z": 0.05556277930736542
            },
            {
              "x": 0.5716895461082458,
              "y": 0.2960446774959564,
              "z": 0.03179847076535225
            },
            {
              "x": 0.5731841325759888,
              "y": 0.25822097063064575,
              "z": 0.06902746111154556
            },
            {
              "x": 0.5626342296600342,
              "y": 0.24370217323303223,
              "z": 0.10107601433992386
            },
            {
              "x": 0.553014874458313,
              "y": 0.23974429070949554,
              "z": 0.12546586990356445
            },
            {
              "x": 0.6077505946159363,
              "y": 0.3024335503578186,
              "z": 0.05752534046769142
            },
            {
              "x": 0.5980077385902405,
              "y": 0.2678384482860565,
              "z": 0.10379602015018463
            },
            {
              "x": 0.5768600106239319,
              "y": 0.2634424865245819,
              "z": 0.1437596082687378
            },
            {
              "x": 0.5599349737167358,
              "y": 0.2682819962501526,
              "z": 0.17431862652301788
            },
            {
              "x": 0.6284650564193726,
              "y": 0.3157549798488617,
              "z": 0.0828126072883606
            },
            {
              "x": 0.6137616038322449,
              "y": 0.28867876529693604,
              "z": 0.12111028283834457
            },
            {
              "x": 0.591657817363739,
              "y": 0.2817431688308716,
              "z": 0.15185698866844177
            },
            {
              "x": 0.5768393278121948,
              "y": 0.2854752540588379,
              "z": 0.17539629340171814
            },
            {
              "x": 0.6412054300308228,
              "y": 0.32995685935020447,
              "z": 0.10784993320703506
            },
            {
              "x": 0.6237643361091614,
              "y": 0.3067997097969055,
              "z": 0.1399119794368744
            },
            {
              "x": 0.6026634573936462,
              "y": 0.3023819029331207,
              "z": 0.16296696662902832
            },
            {
              "x": 0.5897242426872253,
              "y": 0.3064219057559967,
              "z": 0.18272599577903748
            }
          ]
        }
      ]
    },
    {
      "filename": "1826076753920.bmp",
      "hands": [
        {
          "hand_index": 0,
          "landmarks": [
            {
              "x": 0.19891148805618286,
              "y": 0.4205455780029297,
              "z": 3.3074178418246447e-07
            },
            {
              "x": 0.25396594405174255,
              "y": 0.4337637424468994,
              "z": -0.021732399240136147
            },
            {
              "x": 0.2985271215438843,
              "y": 0.4265386760234833,
              "z": -0.027945561334490776
            },
            {
              "x": 0.3264327049255371,
              "y": 0.4189148545265198,
              "z": -0.030816908925771713
            },
            {
              "x": 0.3490583300590515,
              "y": 0.41851964592933655,
              "z": -0.033171817660331726
            },
            {
              "x": 0.28474318981170654,
              "y": 0.3652855157852173,
              "z": -0.018231675028800964
            },
            {
              "x": 0.3070352077484131,
              "y": 0.3332913815975189,
              "z": -0.023769183084368706
            },
            {
              "x": 0.31966397166252136,
              "y": 0.31230050325393677,
              "z": -0.028872933238744736
            },
            {
              "x": 0.3298782706260681,
              "y": 0.29659396409988403,
              "z": -0.03293151035904884
            },
            {
              "x": 0.2544267773628235,
              "y": 0.3558414578437805,
              "z": -0.010149241425096989
            },
            {
              "x": 0.2680613100528717,
              "y": 0.32152849435806274,
              "z": -0.013599111698567867
            },
            {
              "x": 0.2788311839103699,
              "y": 0.29984012246131897,
              "z": -0.01794559694826603
            },
            {
              "x": 0.2858318090438843,
              "y": 0.28556445240974426,
              "z": -0.021460657939314842
            },
            {
              "x": 0.22816020250320435,
              "y": 0.3555104732513428,
              "z": -0.003659989219158888
            },
            {
              "x": 0.2372630089521408,
              "y": 0.32559508085250854,
              "z": -0.007919425144791603
            },
            {
              "x": 0.24388998746871948,
              "y": 0.30945977568626404,
              "z": -0.0136114452034235
            },
            {
              "x": 0.2493436336517334,
              "y": 0.29786133766174316,
              "z": -0.017399974167346954
            },
            {
              "x": 0.20758391916751862,
              "y": 0.36125683784484863,
              "z": 0.0008552861399948597
            },
            {
              "x": 0.21274222433567047,
              "y": 0.34171003103256226,
              "z": -0.004976090043783188
            },
            {
              "x": 0.21659153699874878,
              "y": 0.33114856481552124,
              "z": -0.008875506930053234
            },
            {
              "x": 0.22073566913604736,
              "y": 0.323998361825943,
              "z": -0.010685648769140244
            }
          ]
        },
        {
          "hand_index": 1,
          "landmarks": [
            {
              "x": 0.5351460576057434,
              "y": 0.46802815794944763,
              "z": 1.3848571711605473e-07
            },
            {
              "x": 0.47158753871917725,
              "y": 0.45842495560646057,
              "z": -0.006671301554888487
            },
            {
              "x": 0.4325653910636902,
              "y": 0.42245814204216003,
              "z": -0.004083151929080486
            },
            {
              "x": 0.4139553904533386,
              "y": 0.3889634907245636,
              "z": 0.0003018829447682947
            },
            {
              "x": 0.3967897891998291,
              "y": 0.3688356578350067,
              "z": 0.005887160077691078
            },
            {
              "x": 0.4835655391216278,
              "y": 0.3825487494468689,
              "z": 0.00037269946187734604
            },
            {
              "x": 0.4839164614677429,
              "y": 0.34262943267822266,
              "z": 0.003576512448489666
            },
            {
              "x": 0.4796801209449768,
              "y": 0.3260357975959778,
              "z": 0.006125586107373238
            },
            {
              "x": 0.47267797589302063,
              "y": 0.3162105679512024,
              "z": 0.007983389310538769
            },
            {
              "x": 0.5226806998252869,
              "y": 0.3838410973548889,
              "z": 0.00235655065625906
            },
            {
              "x": 0.5314667224884033,
              "y": 0.3457520604133606,
              "z": 0.009982552379369736
            },
            {
              "x": 0.5324631929397583,
              "y": 0.3270043432712555,
              "z": 0.012729217298328876
            },
            {
              "x": 0.532762885093689,
              "y": 0.3148742616176605,
              "z": 0.01341953594237566
            },
            {
              "x": 0.5549426674842834,
              "y": 0.3933953642845154,
              "z": 0.003373074112460017
            },
            {
              "x": 0.566746711730957,
              "y": 0.3619740605354309,
              "z": 0.005791807547211647
            },
            {
              "x": 0.5725797414779663,
              "y": 0.3438929319381714,
              "z": 0.0050687179900705814
            },
            {
              "x": 0.5757996439933777,
              "y": 0.3313371539115906,
              "z": 0.003966018557548523
            },
            {
              "x": 0.5803132057189941,
              "y": 0.40680596232414246,
              "z": 0.004212344530969858
            },
            {
              "x": 0.5935949087142944,
              "y": 0.38531872630119324,
              "z": 0.005935377441346645
            },
            {
              "x": 0.6006285548210144,
              "y": 0.3732582628726959,
              "z": 0.008969469927251339
            },
            {
              "x": 0.6056497693061829,
              "y": 0.3637818992137909,
              "z": 0.011185886338353157
            }
          ]
        }
      ]
    },
    {
      "filename": "1826176630784.bmp",
      "hands": [
        {
          "hand_index": 0,
          "landmarks": [
            {
              "x": 0.20977066457271576,
              "y": 0.433416485786438,
              "z": 5.635984052787535e-07
            },
            {
              "x": 0.27459198236465454,
              "y": 0.4058058559894562,
              "z": -0.01009325310587883
            },
            {
              "x": 0.3123737573623657,
              "y": 0.3827113211154938,
              "z": -0.0008029493037611246
            },
            {
              "x": 0.34044957160949707,
              "y": 0.3706870377063751,
              "z": 0.009249990805983543
            },
            {
              "x": 0.36576536297798157,
              "y": 0.3576759397983551,
              "z": 0.02146710269153118
            },
            {
              "x": 0.2633499205112457,
              "y": 0.35445091128349304,
              "z": 0.06473387032747269
            },
            {
              "x": 0.26876047253608704,
              "y": 0.3315022587776184,
              "z": 0.10467910766601562
            },
            {
              "x": 0.27535897493362427,
              "y": 0.31987354159355164,
              "z": 0.12945584952831268
            },
            {
              "x": 0.2800902724266052,
              "y": 0.31223705410957336,
              "z": 0.146689772605896
            },
            {
              "x": 0.24724917113780975,
              "y": 0.36341190338134766,
              "z": 0.08335358649492264
            },
            {
              "x": 0.255337119102478,
              "y": 0.3434816896915436,
              "z": 0.13442420959472656
            },
            {
              "x": 0.26633593440055847,
              "y": 0.33499836921691895,
              "z": 0.1595132052898407
            },
            {
              "x": 0.2748086154460907,
              "y": 0.3294277489185333,
              "z": 0.17722557485103607
            },
            {
              "x": 0.23637408018112183,
              "y": 0.3750746250152588,
              "z": 0.09758114069700241
            },
            {
              "x": 0.24679648876190186,
              "y": 0.3579390048980713,
              "z": 0.1418503373861313
            },
            {
              "x": 0.2588181495666504,
              "y": 0.3492720127105713,
              "z": 0.16119754314422607
            },
            {
              "x": 0.26886314153671265,
              "y": 0.3449811041355133,
              "z": 0.17274866998195648
            },
            {
              "x": 0.23484019935131073,
              "y": 0.3859817087650299,
              "z": 0.10839538276195526
            },
            {
              "x": 0.24596631526947021,
              "y": 0.3729637861251831,
              "z": 0.14491567015647888
            },
            {
              "x": 0.2563299834728241,
              "y": 0.3669823408126831,
              "z": 0.16345767676830292
            },
            {
              "x": 0.26335349678993225,
              "y": 0.3638826906681061,
              "z": 0.17714360356330872
            }
          ]
        },
        {
          "hand_index": 1,
          "landmarks": [
            {
              "x": 0.5500805974006653,
              "y": 0.45868104696273804,
              "z": 1.7982601718813385e-07
            },
            {
              "x": 0.47647351026535034,
              "y": 0.43558454513549805,
              "z": -0.0032035233452916145
            },
            {
              "x": 0.4431164860725403,
              "y": 0.3982119858264923,
              "z": 0.011669889092445374
            },
            {
              "x": 0.42743170261383057,
              "y": 0.36730635166168213,
              "z": 0.029541505500674248
            },
            {
              "x": 0.4140664041042328,
              "y": 0.34463074803352356,
              "z": 0.05341062322258949
            },
            {
              "x": 0.49990084767341614,
              "y": 0.3659946024417877,
              "z": 0.048193253576755524
            },
            {
              "x": 0.4941823482513428,
              "y": 0.32766851782798767,
              "z": 0.08255020529031754
            },
            {
              "x": 0.4764878451824188,
              "y": 0.32455897331237793,
              "z": 0.11041265726089478
            },
            {
              "x": 0.46856430172920227,
              "y": 0.3326854109764099,
              "z": 0.1317962408065796
            },
            {
              "x": 0.532548189163208,
              "y": 0.3737103044986725,
              "z": 0.06864593178033829
            },
            {
              "x": 0.5289265513420105,
              "y": 0.338030606508255,
              "z": 0.10940545797348022
            },
            {
              "x": 0.5131986141204834,
              "y": 0.33544766902923584,
              "z": 0.14001694321632385
            },
            {
              "x": 0.5033383965492249,
              "y": 0.3385504484176636,
              "z": 0.1633239984512329
            },
            {
              "x": 0.554957926273346,
              "y": 0.38828274607658386,
              "z": 0.08656398206949234
            },
            {
              "x": 0.5536264777183533,
              "y": 0.3602064847946167,
              "z": 0.123190738260746
            },
            {
              "x": 0.5411302447319031,
              "y": 0.3550339341163635,
              "z": 0.14742687344551086
            },
            {
              "x": 0.5315347909927368,
              "y": 0.3573927581310272,
              "z": 0.16425521671772003
            },
            {
              "x": 0.5686054825782776,
              "y": 0.4059694707393646,
              "z": 0.10313872247934341
            },
            {
              "x": 0.5695683360099792,
              "y": 0.38777956366539,
              "z": 0.13558433949947357
            },
            {
              "x": 0.5618903636932373,
              "y": 0.38512280583381653,
              "z": 0.15464498102664948
            },
            {
              "x": 0.558557391166687,
              "y": 0.3886271119117737,
              "z": 0.16903503239154816
            }
          ]
        }
      ]
    },
    {
      "filename": "1826676539392.bmp",
      "hands": [
        {
          "hand_index": 0,
          "landmarks": [
            {
              "x": 0.48758620023727417,
              "y": 0.49304699897766113,
              "z": 1.9311019627821224e-07
            },
            {
              "x": 0.5231882333755493,
              "y": 0.45184046030044556,
              "z": -0.015974150970578194
            },
            {
              "x": 0.5322651267051697,
              "y": 0.40869140625,
              "z": -0.01753421127796173
            },
            {
              "x": 0.524936854839325,
              "y": 0.3720504939556122,
              "z": -0.019697783514857292
            },
            {
              "x": 0.5089746713638306,
              "y": 0.3471115827560425,
              "z": -0.02103785239160061
            },
            {
              "x": 0.46235185861587524,
              "y": 0.39370426535606384,
              "z": 0.00941699929535389
            },
            {
              "x": 0.4396730065345764,
              "y": 0.35879239439964294,
              "z": -0.003345613367855549
            },
            {
              "x": 0.4379989802837372,
              "y": 0.3420182764530182,
              "z": -0.016810068860650063
            },
            {
              "x": 0.44284114241600037,
              "y": 0.33292141556739807,
              "z": -0.02443067543208599
            },
            {
              "x": 0.4324664771556854,
              "y": 0.4014450013637543,
              "z": 0.00918570440262556
            },
            {
              "x": 0.40013667941093445,
              "y": 0.36364126205444336,
              "z": 0.001997084356844425
            },
            {
              "x": 0.38277989625930786,
              "y": 0.34152430295944214,
              "z": -0.009572411887347698
            },
            {
              "x": 0.3715057075023651,
              "y": 0.32371798157691956,
              "z": -0.018153171986341476
            },
            {
              "x": 0.4071672558784485,
              "y": 0.41403400897979736,
              "z": 0.0042212000116705894
            },
            {
              "x": 0.37534624338150024,
              "y": 0.37863194942474365,
              "z": -0.004612342920154333
            },
            {
              "x": 0.35729584097862244,
              "y": 0.35673609375953674,
              "z": -0.013680889271199703
            },
            {
              "x": 0.3450396656990051,
              "y": 0.338422030210495,
              "z": -0.019574115052819252
            },
            {
              "x": 0.3843402862548828,
              "y": 0.43242910504341125,
              "z": -0.003072557272389531
            },
            {
              "x": 0.3570729196071625,
              "y": 0.40392005443573,
              "z": -0.010541528463363647
            },
            {
              "x": 0.3409230411052704,
              "y": 0.38483813405036926,
              "z": -0.014123005792498589
            },
            {
              "x": 0.32732751965522766,
              "y": 0.36693301796913147,
              "z": -0.016282279044389725
            }
          ]
        },
        {
          "hand_index": 1,
          "landmarks": [
            {
              "x": 0.19793447852134705,
              "y": 0.4574122428894043,
              "z": 1.8828343684162974e-07
            },
            {
              "x": 0.1519014835357666,
              "y": 0.43150290846824646,
              "z": 0.011609912849962711
            },
            {
              "x": 0.13575118780136108,
              "y": 0.40679654479026794,
              "z": 0.029535343870520592
            },
            {
              "x": 0.13599786162376404,
              "y": 0.38389524817466736,
              "z": 0.04061691090464592
            },
            {
              "x": 0.14099174737930298,
              "y": 0.36318135261535645,
              "z": 0.05116963014006615
            },
            {
              "x": 0.20246641337871552,
              "y": 0.39501476287841797,
              "z": 0.08065629750490189
            },
            {
              "x": 0.2046949714422226,
              "y": 0.3704215884208679,
              "z": 0.10488403588533401
            },
            {
              "x": 0.20938655734062195,
              "y": 0.35369616746902466,
              "z": 0.11019279807806015
            },
            {
              "x": 0.2136383354663849,
              "y": 0.34103888273239136,
              "z": 0.11129127442836761
            },
            {
              "x": 0.2308783382177353,
              "y": 0.393558144569397,
              "z": 0.07331366837024689
            },
            {
              "x": 0.24458175897598267,
              "y": 0.3636363744735718,
              "z": 0.10190784931182861
            },
            {
              "x": 0.25157251954078674,
              "y": 0.34397029876708984,
              "z": 0.10293751209974289
            },
            {
              "x": 0.26019904017448425,
              "y": 0.32918238639831543,
              "z": 0.100193090736866
            },
            {
              "x": 0.2562910318374634,
              "y": 0.39477595686912537,
              "z": 0.061166927218437195
            },
            {
              "x": 0.27166759967803955,
              "y": 0.3661041259765625,
              "z": 0.08208322525024414
            },
            {
              "x": 0.27859434485435486,
              "y": 0.3446303606033325,
              "z": 0.08188792318105698
            },
            {
              "x": 0.2853768467903137,
              "y": 0.3297557234764099,
              "z": 0.07857803255319595
            },
            {
              "x": 0.28131237626075745,
              "y": 0.4005697965621948,
              "z": 0.04729900509119034
            },
            {
              "x": 0.2989226281642914,
              "y": 0.3746568262577057,
              "z": 0.06338777393102646
            },
            {
              "x": 0.30719485878944397,
              "y": 0.3579169511795044,
              "z": 0.06967157125473022
            },
            {
              "x": 0.31223416328430176,
              "y": 0.34437882900238037,
              "z": 0.07201363146305084
            }
          ]
        }
      ]
    },
    {
      "filename": "1828409442304.bmp",
      "hands": [
        {
          "hand_index": 0,
          "landmarks": [
            {
              "x": 0.5727936625480652,
              "y": 0.46502459049224854,
              "z": 4.7386248525072006e-07
            },
            {
              "x": 0.5170000195503235,
              "y": 0.4878495931625366,
              "z": -0.03374837711453438
            },
            {
              "x": 0.4622145891189575,
              "y": 0.4825064241886139,
              "z": -0.048923101276159286
            },
            {
              "x": 0.41628870368003845,
              "y": 0.4673372507095337,
              "z": -0.057711489498615265
            },
            {
              "x": 0.37592756748199463,
              "y": 0.4557490944862366,
              "z": -0.06506882607936859
            },
            {
              "x": 0.44945812225341797,
              "y": 0.4229501187801361,
              "z": -0.029821475967764854
            },
            {
              "x": 0.4019647240638733,
              "y": 0.39322397112846375,
              "z": -0.03807612136006355
            },
            {
              "x": 0.3755633533000946,
              "y": 0.3799628019332886,
              "z": -0.045235659927129745
            },
            {
              "x": 0.35698992013931274,
              "y": 0.3712824583053589,
              "z": -0.049984876066446304
            },
            {
              "x": 0.4744928181171417,
              "y": 0.40294793248176575,
              "z": -0.019417623057961464
            },
            {
              "x": 0.4215904474258423,
              "y": 0.37266454100608826,
              "z": -0.025407804176211357
            },
            {
              "x": 0.38640955090522766,
              "y": 0.35380083322525024,
              "z": -0.03482448309659958
            },
            {
              "x": 0.358525812625885,
              "y": 0.3400232493877411,
              "z": -0.04231834039092064
            },
            {
              "x": 0.5024255514144897,
              "y": 0.39366522431373596,
              "z": -0.011340862140059471
            },
            {
              "x": 0.4592522978782654,
              "y": 0.36113011837005615,
              "z": -0.02001548372209072
            },
            {
              "x": 0.43211695551872253,
              "y": 0.3398503065109253,
              "z": -0.03106576018035412
            },
            {
              "x": 0.410285085439682,
              "y": 0.32347530126571655,
              "z": -0.039091501384973526
            },
            {
              "x": 0.5292518138885498,
              "y": 0.39094769954681396,
              "z": -0.005218901205807924
            },
            {
              "x": 0.5007503032684326,
              "y": 0.36460161209106445,
              "z": -0.014868614263832569
            },
            {
              "x": 0.48293396830558777,
              "y": 0.3483864367008209,
              "z": -0.020933153107762337
            },
            {
              "x": 0.4688001871109009,
              "y": 0.33485865592956543,
              "z": -0.02478373982012272
            }
          ]
        },
        {
          "hand_index": 1,
          "landmarks": [
            {
              "x": 0.13510662317276,
              "y": 0.4308108389377594,
              "z": 2.3440796326212876e-07
            },
            {
              "x": 0.18153169751167297,
              "y": 0.45572125911712646,
              "z": -8.21884605102241e-05
            },
            {
              "x": 0.23079144954681396,
              "y": 0.45802149176597595,
              "z": 0.002154425485059619
            },
            {
              "x": 0.26302358508110046,
              "y": 0.44642573595046997,
              "z": 0.00550305750221014
            },
            {
              "x": 0.28402507305145264,
              "y": 0.44028639793395996,
              "z": 0.008872701786458492
            },
            {
              "x": 0.2684374749660492,
              "y": 0.402462899684906,
              "z": -0.005211725365370512
            },
            {
              "x": 0.32451993227005005,
              "y": 0.39006567001342773,
              "z": -0.011196529492735863
            },
            {
              "x": 0.3500599265098572,
              "y": 0.38710686564445496,
              "z": -0.015541904605925083
            },
            {
              "x": 0.36472901701927185,
              "y": 0.3869852125644684,
              "z": -0.017557533457875252
            },
            {
              "x": 0.2527753710746765,
              "y": 0.3784886300563812,
              "z": -0.0074347746558487415
            },
            {
              "x": 0.3129369616508484,
              "y": 0.3571326732635498,
              "z": -0.01282530091702938
            },
            {
              "x": 0.3431778848171234,
              "y": 0.34921783208847046,
              "z": -0.01608164794743061
            },
            {
              "x": 0.36421576142311096,
              "y": 0.345059871673584,
              "z": -0.017471615225076675
            },
            {
              "x": 0.23024143278598785,
              "y": 0.3619137108325958,
              "z": -0.009807617403566837
            },
            {
              "x": 0.2886430621147156,
              "y": 0.33718574047088623,
              "z": -0.016797075048089027
            },
            {
              "x": 0.32418403029441833,
              "y": 0.32316768169403076,
              "z": -0.024585828185081482
            },
            {
              "x": 0.352096825838089,
              "y": 0.31360286474227905,
              "z": -0.029396334663033485
            },
            {
              "x": 0.20423446595668793,
              "y": 0.3516291379928589,
              "z": -0.01113820355385542
            },
            {
              "x": 0.241907998919487,
              "y": 0.32625141739845276,
              "z": -0.018106888979673386
            },
            {
              "x": 0.26701095700263977,
              "y": 0.3116486668586731,
              "z": -0.02218478173017502
            },
            {
              "x": 0.2898278832435608,
              "y": 0.30107372999191284,
              "z": -0.024068836122751236
            }
          ]
        }
      ]
    }
  ]
}